libnmfd/__init__.py
libnmfd/core/__init__.py
libnmfd/core/nmf.py
libnmfd/core/nmfconv.py
libnmfd/core/nmfdiag.py
libnmfd/dsp/__init__.py
libnmfd/dsp/algorithms.py
libnmfd/dsp/filters.py
libnmfd/dsp/transforms.py
libnmfd/utils/__init__.py
libnmfd/utils/core_utils.py
libnmfd/utils/dsp_utils.py
libnmfd-1.0.0.dist-info/LICENSE
libnmfd-1.0.0.dist-info/METADATA
libnmfd-1.0.0.dist-info/WHEEL
libnmfd-1.0.0.dist-info/top_level.txt
libnmfd-1.0.0.dist-info/RECORD
