Metadata-Version: 2.1
Name: libnmfd
Version: 1.0.0
Summary: libnmfd: Music Processing Applications of Nonnegative Matrix Factorization
Home-page: https://github.com/groupmm/libnmfd
Download-URL: https://github.com/groupmm/libnmfd
Author: Patricio López-Serrano, Christian Dittmar, Yigitcan Özer and Meinard Müller
Author-email: christian.dittmar@iis.fraunhofer.de
License: MIT
Keywords: audio music sound nmf decomposition
Classifier: License :: OSI Approved :: MIT License
Classifier: Programming Language :: Python
Classifier: Intended Audience :: Developers
Classifier: Topic :: Multimedia :: Sound/Audio :: Analysis
Classifier: Programming Language :: Python :: 3
Requires-Python: >=3.8, <4.0
License-File: LICENSE
Requires-Dist: ipython <8.0.0,>=7.10.0
Requires-Dist: jupyter >=1.0.0
Requires-Dist: matplotlib <4.0.0,>=3.1.0
Requires-Dist: numpy <2.0.0,>=1.17.0
Requires-Dist: pandas <2.0.0,>=1.0.0
Requires-Dist: pysoundfile <1.0.0,>=0.9.0
Requires-Dist: scipy <2.0.0,>=1.7.0
Requires-Dist: tqdm >=4.0.0
Provides-Extra: docs
Requires-Dist: sphinx ==4.0.* ; extra == 'docs'
Requires-Dist: sphinx-rtd-theme ==0.5.* ; extra == 'docs'
Provides-Extra: tests
Requires-Dist: pytest ==6.2.* ; extra == 'tests'
